{"userId":"113","gender":1,"tenure":126,"active_days_count":24,"session_count":24,"song_count":1598,"total_length":400094.13201999967,"paid_sessions":1797,"paid_sessions_length":380538.79624999943,"free_sessions":98,"free_sessions_length":19555.33577000001,"paid_session_share":74.875,"About":1,"Add Friend":32,"Add to Playlist":50,"Downgrade":16,"Error":3,"Help":7,"Home":72,"Logout":18,"NextSong":1585,"Roll Advert":1,"Save Settings":3,"Settings":8,"Submit Downgrade":0,"Submit Upgrade":1,"Thumbs Down":12,"Thumbs Up":82,"Upgrade":4,"user_churn_flag":0}
{"userId":"30","gender":0,"tenure":65,"active_days_count":28,"session_count":32,"song_count":1423,"total_length":359808.2456399997,"paid_sessions":675,"paid_sessions_length":145731.2657799998,"free_sessions":1100,"free_sessions_length":214076.97985999982,"paid_session_share":21.09375,"About":3,"Add Friend":25,"Add to Playlist":47,"Downgrade":6,"Error":1,"Help":5,"Home":70,"Logout":20,"NextSong":1417,"Roll Advert":72,"Save Settings":1,"Settings":13,"Submit Downgrade":1,"Submit Upgrade":1,"Thumbs Down":17,"Thumbs Up":62,"Upgrade":14,"user_churn_flag":0}
