{"userId":"97","gender":1,"tenure":90,"active_days_count":28,"session_count":30,"song_count":1974,"total_length":491231.4963500007,"paid_sessions":1940,"paid_sessions_length":401124.67779000034,"free_sessions":464,"free_sessions_length":90106.81856000003,"paid_session_share":64.66666666666667,"About":5,"Add Friend":32,"Add to Playlist":61,"Downgrade":17,"Error":1,"Help":17,"Home":100,"Logout":34,"NextSong":1975,"Roll Advert":24,"Save Settings":2,"Settings":12,"Submit Downgrade":0,"Submit Upgrade":1,"Thumbs Down":12,"Thumbs Up":108,"Upgrade":3,"user_churn_flag":0}
